MANIFEST.in
requirements.txt
setup.cfg
setup.py
napalm_iosxr/__init__.py
napalm_iosxr/constants.py
napalm_iosxr/iosxr.py
napalm_iosxr.egg-info/PKG-INFO
napalm_iosxr.egg-info/SOURCES.txt
napalm_iosxr.egg-info/dependency_links.txt
napalm_iosxr.egg-info/requires.txt
napalm_iosxr.egg-info/top_level.txt
napalm_iosxr/templates/delete_ntp_peers.j2
napalm_iosxr/templates/delete_ntp_servers.j2
napalm_iosxr/templates/delete_probes.j2
napalm_iosxr/templates/delete_snmp_config.j2
napalm_iosxr/templates/delete_users.j2
napalm_iosxr/templates/schedule_probes.j2
napalm_iosxr/templates/set_hostname.j2
napalm_iosxr/templates/set_ntp_peers.j2
napalm_iosxr/templates/set_ntp_servers.j2
napalm_iosxr/templates/set_probes.j2
napalm_iosxr/templates/set_users.j2
napalm_iosxr/templates/snmp_config.j2